package/102103267.py
package/__init__.py
topsis_pulkit_102103267-1.0.dist-info/LICENSE
topsis_pulkit_102103267-1.0.dist-info/METADATA
topsis_pulkit_102103267-1.0.dist-info/WHEEL
topsis_pulkit_102103267-1.0.dist-info/entry_points.txt
topsis_pulkit_102103267-1.0.dist-info/top_level.txt
topsis_pulkit_102103267-1.0.dist-info/RECORD
