Metadata-Version: 2.1
Name: topsis_pulkit_102103267
Version: 1.0
Summary: TOPSIS
Author: Pulkit Arora
Author-email: pulkitarora8690@gmail.com
License: MIT
Keywords: TOPSIS
Classifier: Development Status :: 3 - Alpha
Classifier: Intended Audience :: Developers
Classifier: Topic :: Software Development :: Build Tools
Classifier: License :: OSI Approved :: MIT License
Classifier: Programming Language :: Python :: 3
License-File: LICENSE
Requires-Dist: numpy
Requires-Dist: pandas
